setup.py
one_year_ago/__init__.py
one_year_ago/one_year_ago.py
one_year_ago.egg-info/PKG-INFO
one_year_ago.egg-info/SOURCES.txt
one_year_ago.egg-info/dependency_links.txt
one_year_ago.egg-info/requires.txt
one_year_ago.egg-info/top_level.txt