Metadata-Version: 1.1
Name: one-year-ago
Version: 0.5
Summary: Easy way to get the same day scenario (week, weekday, working day and holiday) for a previous year.
Home-page: https://www.gisce.net
Author: GISCE Enginyeria, SL
Author-email: devel@gisce.net
License: General Public Licence 3
Platform: UNKNOWN
Provides: one_year_ago
